js2-0.1.0.dist-info/licenses/LICENSE
js2_pkg/__init__.py
js2_pkg/capture.py
js2_pkg/cli.py
js2_pkg/server.py
js2_pkg/static/viewer.html
js2-0.1.0.dist-info/METADATA
js2-0.1.0.dist-info/WHEEL
js2-0.1.0.dist-info/entry_points.txt
js2-0.1.0.dist-info/top_level.txt
js2-0.1.0.dist-info/RECORD
