Metadata-Version: 2.4
Name: js2
Version: 0.1.0
Summary: Just Screen Share - Share your screen with a public URL
Home-page: https://github.com/sirojiddindushaev/js2
Author: Sirojiddin Dushaev
Author-email: sirojiddin@example.com
License: MIT
Project-URL: Homepage, https://github.com/sirojiddindushaev/js2
Project-URL: Documentation, https://github.com/sirojiddindushaev/js2#readme
Project-URL: Repository, https://github.com/sirojiddindushaev/js2
Project-URL: Issues, https://github.com/sirojiddindushaev/js2/issues
Keywords: screen-share,screenshare,screen,share,ngrok,tunnel,remote
Classifier: Development Status :: 4 - Beta
Classifier: Intended Audience :: Developers
Classifier: Intended Audience :: End Users/Desktop
Classifier: License :: OSI Approved :: MIT License
Classifier: Operating System :: OS Independent
Classifier: Programming Language :: Python :: 3
Classifier: Programming Language :: Python :: 3.8
Classifier: Programming Language :: Python :: 3.9
Classifier: Programming Language :: Python :: 3.10
Classifier: Programming Language :: Python :: 3.11
Classifier: Programming Language :: Python :: 3.12
Classifier: Topic :: Communications
Classifier: Topic :: Multimedia :: Video
Classifier: Topic :: Internet :: WWW/HTTP
Requires-Python: >=3.8
License-File: LICENSE
Requires-Dist: fastapi>=0.100.0
Requires-Dist: uvicorn>=0.23.0
Requires-Dist: websockets>=11.0
Requires-Dist: mss>=9.0.0
Requires-Dist: Pillow>=10.0.0
Requires-Dist: pyngrok>=7.0.0
Dynamic: author-email
Dynamic: home-page
Dynamic: license-file
Dynamic: requires-python
